[
  [
    {
      "command": "SHOW_FRAME",
      "frame": 0
    },
    {
      "command": "SHOW_BACKGROUND",
      "background": "STARBASE_EXTERIOR"
    },
    {
      "command": "SHOW_CENTERED_TEXT",
      "text": "Spacebase Chip-1\nSmall Magellanic Cloud",
      "chirp": 76
    },
    {
      "command": "SHOW_BACKGROUND",
      "background": "STARBASE"
    },
    {
      "command": "PLAY_MUSIC",
      "track": "Ballad of St. Janet"
    },
    {
      "command": "SHOW_SPRITE",
      "sprite": "AVA",
      "slot": 0,
      "face": 5,
      "x": 4
    },
    {
      "command": "SHOW_SPRITE",
      "sprite": "CINDY",
      "slot": 1,
      "face": 1,
      "x": 9
    },
    {
      "command": "SHOW_SPRITE",
      "sprite": "NELEHU",
      "slot": 2,
      "face": 0,
      "x": 12
    },
    {
      "command": "SHOW_SPRITE",
      "sprite": "BOB",
      "slot": 3,
      "face": 1,
      "x": 15
    },
    {
      "command": "SHOW_TEXT",
      "text": "AVA: Wow! What an awful day! Everything's gone wrong today!"
    },
    {
      "command": "SHOW_SPRITE",
      "slot": 1,
      "face": 0
    },
    {
      "command": "SHOW_TEXT",
      "text": "CINDY: That's why I, Captain Cynthia \"Cindy\" Palisade of the Spacebase Chip--"
    },
    {
      "command": "SHOW_SPRITE",
      "slot": 3,
      "face": 0
    },
    {
      "command": "SHOW_TEXT",
      "text": "BOB: ..."
    },
    {
      "command": "SHOW_SPRITE",
      "slot": 1,
      "face": 3
    },
    {
      "command": "SHOW_TEXT",
      "text": "CINDY: I know, Lieutenant Bob, you know who I am."
    },
    {
      "command": "SHOW_SPRITE",
      "slot": 3,
      "face": 1
    },
    {
      "command": "SHOW_SPRITE",
      "slot": 1,
      "face": 2
    },
    {
      "command": "SHOW_TEXT",
      "text": "CINDY: I've just been so excited since getting my promotion."
    },
    {
      "command": "SHOW_SPRITE",
      "slot": 1,
      "face": 0
    },
    {
      "command": "SHOW_TEXT",
      "text": "CINDY: In any case, ever since the no communication theorem was lifted, I know you all have been glued to the news coming from Earth."
    },
    {
      "command": "SHOW_SPRITE",
      "slot": 1,
      "face": 5
    },
    {
      "command": "SHOW_SPRITE",
      "sprite": "AVA",
      "slot": 0,
      "face": 2
    },
    {
      "command": "SHOW_TEXT",
      "text": "AVA: Earth?! My food replicator's been out all day and no one has done anything to fix it! I don't even remember which planet Earth is!"
    },
    {
      "command": "SHOW_SPRITE",
      "face": 5
    },
    {
      "command": "SHOW_SPRITE",
      "slot": 2,
      "face": 4
    },
    {
      "command": "SHOW_TEXT",
      "text": "NELEHU: Perhaps it was due to misuse. The amount of matter in the universe is limited, after all."
    },
    {
      "command": "SHOW_SPRITE",
      "sprite": "AVA",
      "slot": 0,
      "face": 2
    },
    {
      "command": "SHOW_TEXT",
      "text": "AVA: Excuse me?!"
    },
    {
      "command": "SHOW_SPRITE",
      "slot": 2,
      "face": 0
    },
    {
      "command": "SHOW_SPRITE",
      "slot": 1,
      "face": 1
    },
    {
      "command": "PLAY_MUSIC",
      "track": "Evan S. Sense"
    },
    {
      "command": "SHOW_TEXT",
      "text": "CINDY: In any case! The Earth has been encased in a quantum field! Quantum ships patrol the Milky Way galaxy! The Amalgamation of Worlds... is at war."
    },
    {
      "command": "SHOW_SPRITE",
      "slot": 0,
      "face": 6
    },
    {
      "command": "SHOW_TEXT",
      "text": "AVA: Question. What's a war?"
    },
    {
      "command": "SHOW_SPRITE",
      "slot": 1,
      "face": 0
    },
    {
      "command": "SHOW_TEXT",
      "text": "CINDY: And I was about to say, the only one in the entire Amalgamation who's defeated quantum before... is Ava."
    },
    {
      "command": "SHOW_SPRITE",
      "slot": 0,
      "face": 0
    },
    {
      "command": "SHOW_SPRITE",
      "slot": 3,
      "face": 0
    },
    {
      "command": "SHOW_TEXT",
      "text": "BOB: ..."
    },
    {
      "command": "SHOW_SPRITE",
      "slot": 3,
      "face": 1
    },
    {
      "command": "SHOW_SPRITE",
      "slot": 1,
      "face": 3
    },
    {
      "command": "SHOW_TEXT",
      "text": "CINDY: I don't think I'd have put it like that, Lieutenant, but you have a good point. Ava, it's been awhile since you've done quantum stuff. Do you remember how it works?"
    },
    {
      "command": "SHOW_SPRITE",
      "slot": 0,
      "face": 4
    },
    {
      "command": "SHOW_SPRITE",
      "slot": 1,
      "face": 0
    },
    {
      "command": "SHOW_TEXT",
      "text": "AVA: Of course I remember! You grab the photon and the antiphoton and they merge, and then there's... there's a cat involved, and... well, Lily helped me with the math a bit, but I'm sure it'll come right back!"
    },
    {
      "command": "SHOW_SPRITE",
      "slot": 2,
      "face": 3
    },
    {
      "command": "SHOW_TEXT",
      "text": "NELEHU: Don't worry. Perhaps our new overlords will be more respectful of limited resources."
    },
    {
      "command": "SHOW_SPRITE",
      "slot": 2,
      "face": 0
    },
    {
      "command": "SHOW_SPRITE",
      "slot": 0,
      "face": 2
    },
    {
      "command": "SHOW_TEXT",
      "text": "AVA: I'm sure it'll come right back to me if I try!"
    },
    {
      "command": "SHOW_SPRITE",
      "slot": 3,
      "face": 0
    },
    {
      "command": "SHOW_TEXT",
      "text": "BOB: ..."
    },
    {
      "command": "SHOW_SPRITE",
      "slot": 3,
      "face": 1
    },
    {
      "command": "SHOW_SPRITE",
      "slot": 1,
      "face": 2
    },
    {
      "command": "SHOW_TEXT",
      "text": "CINDY: That's a great idea, Lieutenant! Nelehu, you can set up a quantum field in the landing bay. I'm sure Ava will get right back into the swing of things with a little practice!"
    },
    {
      "command": "SHOW_SPRITE",
      "slot": 1,
      "face": 0
    },
    {
      "command": "SHOW_SPRITE",
      "slot": 0,
      "face": 0
    },
    {
      "command": "SHOW_TEXT",
      "text": "AVA: Yeah... I'll do just fine..."
    },
    {
      "command": "SHOW_TEXT",
      "text": "*gulp*"
    }
  ],
  [
    {
      "command": "SHOW_FRAME",
      "frame": 0
    },
    {
      "command": "SHOW_BACKGROUND",
      "background": "TRAINING_HALL"
    },
    {
      "command": "PLAY_MUSIC",
      "track": "Ballad of St. Janet"
    },
    {
      "command": "SHOW_SPRITE",
      "slot": 0,
      "sprite": "AVA",
      "face": 1,
      "x": 9
    },
    {
      "command": "SHOW_TEXT",
      "text": "AVA: See! I knew I could do it! So now we need to go and save the Earth! That's the one with the rings, right?"
    },
    {
      "command": "STOP_MUSIC"
    },
    {
      "command": "SHOW_TEXT",
      "text": "NELEHU: This is Lieutenant Nelehu. We have a minor issue.",
      "chirp": 210
    },
    {
      "command": "SHOW_SPRITE",
      "face": 0
    },
    {
      "command": "SHOW_TEXT",
      "text": "CINDY: Minor?! Nelehu, this is no time for understatement!",
      "chirp": 200
    },
    {
      "command": "PLAY_MUSIC",
      "track": "Evan S. Sense"
    },
    {
      "command": "SHOW_TEXT",
      "text": "AVA: What's going on in there?"
    },
    {
      "command": "SHOW_TEXT",
      "text": "CINDY: Hang tight, Ava! You might have to stay in the quantum world just a little longer.",
      "chirp": 200
    },
    {
      "command": "SHOW_SPRITE",
      "face": 2
    },
    {
      "command": "SHOW_TEXT",
      "text": "CINDY: Oh my editor! They're getting into my computer, I swear if they delete any of my manuscripts",
      "chirp": 200
    },
    {
      "command": "SHOW_SPRITE",
      "face": 0
    },
    {
      "command": "SHOW_TEXT",
      "text": "*beep*",
      "chirp": 66
    },
    {
      "command": "SHOW_TEXT",
      "text": "AVA: That's not particularly reassuring..."
    }
  ],
  [
    {
      "command": "SHOW_FRAME",
      "frame": 0
    },
    {
      "command": "SHOW_BACKGROUND",
      "background": "TRAINING_HALL"
    },
    {
      "command": "PLAY_MUSIC",
      "track": "Evan S. Sense"
    },
    {
      "command": "SHOW_SPRITE",
      "slot": 0,
      "sprite": "AVA",
      "face": 0,
      "x": 5
    },
    {
      "command": "SHOW_TEXT",
      "text": "AVA: I don't think these are just test chambers anymore... what's going on in here?"
    },
    {
      "command": "SHOW_TEXT",
      "text": "???: Wouldn't you like to know!",
      "chirp": 200
    },
    {
      "command": "SHOW_SPRITE",
      "slot": 0,
      "face": 2
    },
    {
      "command": "SHOW_SPRITE",
      "slot": 1,
      "sprite": "GOON",
      "x": 12,
      "face": 2
    },
    {
      "command": "PLAY_MUSIC",
      "track": "Chime 2020"
    },
    {
      "command": "SHOW_TEXT",
      "text": "MAN: Hahaha! Halt in the name of quantum!"
    },
    {
      "command": "SHOW_SPRITE",
      "slot": 1,
      "face": 0
    },
    {
      "command": "SHOW_TEXT",
      "text": "AVA: But we're in an entirely different galaxy! How did you make it over here so quickly?"
    },
    {
      "command": "SHOW_SPRITE",
      "slot": 1,
      "face": 2
    },
    {
      "command": "SHOW_SPRITE",
      "slot": 0,
      "face": 5
    },
    {
      "command": "SHOW_TEXT",
      "text": "MAN: We used quantum teleportation! Haven't you ever heard of spooky action at a distance?"
    },
    {
      "command": "SHOW_TEXT",
      "text": "Now that we've escaped the confines of the black hole, the entire universe will be placed inside a quantum field! It's what you deserve!"
    },
    {
      "command": "SHOW_SPRITE",
      "slot": 1,
      "face": 1
    },
    {
      "command": "SHOW_SPRITE",
      "slot": 0,
      "face": 0
    },
    {
      "command": "SHOW_TEXT",
      "text": "AVA: And what's with the giant eye balls! Those are weirding me out just a little."
    },
    {
      "command": "SHOW_SPRITE",
      "slot": 0,
      "face": 2
    },
    {
      "command": "SHOW_SPRITE",
      "slot": 1,
      "face": 2
    },
    {
      "command": "SHOW_TEXT",
      "text": "MAN: You can't have quantum without the observers!"
    },
    {
      "command": "SHOW_SPRITE",
      "slot": 1,
      "face": 0
    },
    {
      "command": "SHOW_SPRITE",
      "slot": 0,
      "face": 0
    },
    {
      "command": "SHOW_TEXT",
      "text": "AVA: But this all doesn't make sense... I met Schrodinger's Cat, you all just wanted to stay inside the black hole. Why would you leave now? What's changed?"
    },
    {
      "command": "SHOW_SPRITE",
      "slot": 1,
      "face": 2
    },
    {
      "command": "SHOW_SPRITE",
      "slot": 0,
      "face": 2
    },
    {
      "command": "SHOW_TEXT",
      "text": "MAN: Schrodinger's cat is gone! They were weak and lost to the likes of you! We've got new leadership now!"
    },
    {
      "command": "SHOW_SPRITE",
      "slot": 1,
      "face": 3
    },
    {
      "command": "SHOW_TEXT",
      "text": "MAN: But enough talk! Shut up and calculate!"
    }
  ]
]
